sentry_scrubber/__init__.py
sentry_scrubber/scrubber.py
sentry_scrubber/tests/test_init.py
sentry_scrubber/tests/test_scrubber.py
sentry_scrubber/tests/test_utils.py
sentry_scrubber/utils.py
sentry_scrubber-2.3.0.dist-info/LICENSE
sentry_scrubber-2.3.0.dist-info/METADATA
sentry_scrubber-2.3.0.dist-info/WHEEL
sentry_scrubber-2.3.0.dist-info/RECORD
