Metadata-Version: 2.3
Name: sentry-scrubber
Version: 2.3.0
Summary: A lightweight and flexible Python library for scrubbing sensitive information from Sentry events before they are sent to the server.
License: MIT
Author: Andrei Andreev
Requires-Python: >=3.9.17,<4.0.0
Classifier: License :: OSI Approved :: MIT License
Classifier: Operating System :: OS Independent
Classifier: Programming Language :: Python :: 3
Classifier: Programming Language :: Python :: 3.10
Classifier: Programming Language :: Python :: 3.11
Classifier: Programming Language :: Python :: 3.12
Classifier: Programming Language :: Python :: 3.13
Project-URL: Documentation, https://github.com/drew2a/sentry-scrubber/blob/main/README.md
Project-URL: Homepage, https://github.com/drew2a/sentry-scrubber
